{
  "supplier_code": "BJG52",
  "supplier_name": "METALURGICA FALLGATTER LTDA",
  "semana": "2026-W28",
  "gerado_em": "10/07/2026 10:01",
  "aviso_link": "O link enviado ontem nao estava funcionando. Por favor considerar este novo link.",
  "itens": [
    {
      "part_number": "87480926",
      "supplier_code": "BJG52",
      "supplier_name": "METALURGICA FALLGATTER LTDA",
      "ship_date": "31/08/2026",
      "impact": "3",
      "sharepoint_critico": false,
      "sharepoint_url": "",
      "sharepoint_reason": "",
      "acao_requerida": "Promessa vencida - solicitar nova data",
      "past_due_wmf": 16,
      "firm_jun_wmf": 16,
      "firm_jul_wmf": 0,
      "ultima_nfe": "000525955-001",
      "semana": "2026-W28",
      "data_promessa": "06/07/2026",
      "qty_prometida": 16,
      "comentario": "Promessa vencida - solicitar nova data. Material embarcado 000530018-1"
    }
  ]
}