{
  "supplier_code": "WMFBR",
  "supplier_name": "CNH Brasil WMF",
  "semana": "2026-W30",
  "gerado_em": "21/07/2026 15:55",
  "aviso_link": "O link enviado ontem nao estava funcionando. Por favor considerar este novo link.",
  "itens": [
    {
      "part_number": "47462929",
      "supplier_code": "WMFBR",
      "supplier_name": "CNH Brasil WMF",
      "ship_date": "",
      "impact": "",
      "sharepoint_critico": false,
      "sharepoint_url": "",
      "sharepoint_reason": "",
      "acao_requerida": "Solicitar promessa",
      "past_due_wmf": 150,
      "firm_jun_wmf": 0,
      "firm_jul_wmf": 0,
      "ultima_nfe": "",
      "semana": "2026-W30",
      "data_promessa": "",
      "qty_prometida": "",
      "comentario": "Solicitar promessa."
    },
    {
      "part_number": "47567456",
      "supplier_code": "WMFBR",
      "supplier_name": "CNH Brasil WMF",
      "ship_date": "",
      "impact": "",
      "sharepoint_critico": false,
      "sharepoint_url": "",
      "sharepoint_reason": "",
      "acao_requerida": "Solicitar promessa",
      "past_due_wmf": 300,
      "firm_jun_wmf": 0,
      "firm_jul_wmf": 0,
      "ultima_nfe": "",
      "semana": "2026-W30",
      "data_promessa": "",
      "qty_prometida": "",
      "comentario": "Solicitar promessa."
    },
    {
      "part_number": "47632509",
      "supplier_code": "WMFBR",
      "supplier_name": "CNH Brasil WMF",
      "ship_date": "",
      "impact": "",
      "sharepoint_critico": false,
      "sharepoint_url": "",
      "sharepoint_reason": "",
      "acao_requerida": "Solicitar promessa",
      "past_due_wmf": 150,
      "firm_jun_wmf": 0,
      "firm_jul_wmf": 0,
      "ultima_nfe": "",
      "semana": "2026-W30",
      "data_promessa": "",
      "qty_prometida": "",
      "comentario": "Solicitar promessa."
    },
    {
      "part_number": "47749392",
      "supplier_code": "WMFBR",
      "supplier_name": "CNH Brasil WMF",
      "ship_date": "",
      "impact": "",
      "sharepoint_critico": false,
      "sharepoint_url": "",
      "sharepoint_reason": "",
      "acao_requerida": "Solicitar promessa",
      "past_due_wmf": 20,
      "firm_jun_wmf": 0,
      "firm_jul_wmf": 0,
      "ultima_nfe": "",
      "semana": "2026-W30",
      "data_promessa": "",
      "qty_prometida": "",
      "comentario": "Solicitar promessa."
    },
    {
      "part_number": "47783349",
      "supplier_code": "WMFBR",
      "supplier_name": "CNH Brasil WMF",
      "ship_date": "",
      "impact": "",
      "sharepoint_critico": false,
      "sharepoint_url": "",
      "sharepoint_reason": "",
      "acao_requerida": "Solicitar promessa",
      "past_due_wmf": 25,
      "firm_jun_wmf": 0,
      "firm_jul_wmf": 0,
      "ultima_nfe": "",
      "semana": "2026-W30",
      "data_promessa": "",
      "qty_prometida": "",
      "comentario": "Solicitar promessa."
    },
    {
      "part_number": "47793426",
      "supplier_code": "WMFBR",
      "supplier_name": "CNH Brasil WMF",
      "ship_date": "",
      "impact": "",
      "sharepoint_critico": false,
      "sharepoint_url": "",
      "sharepoint_reason": "",
      "acao_requerida": "Solicitar promessa",
      "past_due_wmf": 150,
      "firm_jun_wmf": 0,
      "firm_jul_wmf": 0,
      "ultima_nfe": "",
      "semana": "2026-W30",
      "data_promessa": "",
      "qty_prometida": "",
      "comentario": "Solicitar promessa."
    },
    {
      "part_number": "47800541",
      "supplier_code": "WMFBR",
      "supplier_name": "CNH Brasil WMF",
      "ship_date": "",
      "impact": "",
      "sharepoint_critico": false,
      "sharepoint_url": "",
      "sharepoint_reason": "",
      "acao_requerida": "Solicitar promessa",
      "past_due_wmf": 3,
      "firm_jun_wmf": 0,
      "firm_jul_wmf": 0,
      "ultima_nfe": "000237637-001",
      "semana": "2026-W30",
      "data_promessa": "",
      "qty_prometida": "",
      "comentario": "Solicitar promessa."
    },
    {
      "part_number": "47800586",
      "supplier_code": "WMFBR",
      "supplier_name": "CNH Brasil WMF",
      "ship_date": "",
      "impact": "",
      "sharepoint_critico": false,
      "sharepoint_url": "",
      "sharepoint_reason": "",
      "acao_requerida": "Solicitar promessa",
      "past_due_wmf": 93,
      "firm_jun_wmf": 0,
      "firm_jul_wmf": 0,
      "ultima_nfe": "",
      "semana": "2026-W30",
      "data_promessa": "",
      "qty_prometida": "",
      "comentario": "Solicitar promessa."
    },
    {
      "part_number": "47800590",
      "supplier_code": "WMFBR",
      "supplier_name": "CNH Brasil WMF",
      "ship_date": "",
      "impact": "",
      "sharepoint_critico": false,
      "sharepoint_url": "",
      "sharepoint_reason": "",
      "acao_requerida": "Solicitar promessa",
      "past_due_wmf": 93,
      "firm_jun_wmf": 0,
      "firm_jul_wmf": 0,
      "ultima_nfe": "",
      "semana": "2026-W30",
      "data_promessa": "",
      "qty_prometida": "",
      "comentario": "Solicitar promessa."
    },
    {
      "part_number": "47801157",
      "supplier_code": "WMFBR",
      "supplier_name": "CNH Brasil WMF",
      "ship_date": "",
      "impact": "",
      "sharepoint_critico": false,
      "sharepoint_url": "",
      "sharepoint_reason": "",
      "acao_requerida": "Solicitar promessa",
      "past_due_wmf": 150,
      "firm_jun_wmf": 0,
      "firm_jul_wmf": 0,
      "ultima_nfe": "",
      "semana": "2026-W30",
      "data_promessa": "",
      "qty_prometida": "",
      "comentario": "Solicitar promessa."
    },
    {
      "part_number": "47819163",
      "supplier_code": "WMFBR",
      "supplier_name": "CNH Brasil WMF",
      "ship_date": "",
      "impact": "",
      "sharepoint_critico": false,
      "sharepoint_url": "",
      "sharepoint_reason": "",
      "acao_requerida": "Solicitar promessa",
      "past_due_wmf": 150,
      "firm_jun_wmf": 0,
      "firm_jul_wmf": 0,
      "ultima_nfe": "",
      "semana": "2026-W30",
      "data_promessa": "",
      "qty_prometida": "",
      "comentario": "Solicitar promessa."
    },
    {
      "part_number": "47821777",
      "supplier_code": "WMFBR",
      "supplier_name": "CNH Brasil WMF",
      "ship_date": "",
      "impact": "",
      "sharepoint_critico": false,
      "sharepoint_url": "",
      "sharepoint_reason": "",
      "acao_requerida": "Solicitar promessa",
      "past_due_wmf": 93,
      "firm_jun_wmf": 0,
      "firm_jul_wmf": 0,
      "ultima_nfe": "",
      "semana": "2026-W30",
      "data_promessa": "",
      "qty_prometida": "",
      "comentario": "Solicitar promessa."
    },
    {
      "part_number": "47840433",
      "supplier_code": "WMFBR",
      "supplier_name": "CNH Brasil WMF",
      "ship_date": "",
      "impact": "",
      "sharepoint_critico": false,
      "sharepoint_url": "",
      "sharepoint_reason": "",
      "acao_requerida": "Solicitar promessa",
      "past_due_wmf": 93,
      "firm_jun_wmf": 0,
      "firm_jul_wmf": 0,
      "ultima_nfe": "",
      "semana": "2026-W30",
      "data_promessa": "",
      "qty_prometida": "",
      "comentario": "Solicitar promessa."
    },
    {
      "part_number": "48153235",
      "supplier_code": "WMFBR",
      "supplier_name": "CNH Brasil WMF",
      "ship_date": "",
      "impact": "",
      "sharepoint_critico": false,
      "sharepoint_url": "",
      "sharepoint_reason": "",
      "acao_requerida": "Solicitar promessa",
      "past_due_wmf": 32,
      "firm_jun_wmf": 0,
      "firm_jul_wmf": 0,
      "ultima_nfe": "",
      "semana": "2026-W30",
      "data_promessa": "",
      "qty_prometida": "",
      "comentario": "Solicitar promessa."
    },
    {
      "part_number": "51549217",
      "supplier_code": "WMFBR",
      "supplier_name": "CNH Brasil WMF",
      "ship_date": "",
      "impact": "",
      "sharepoint_critico": false,
      "sharepoint_url": "",
      "sharepoint_reason": "",
      "acao_requerida": "Solicitar promessa",
      "past_due_wmf": 93,
      "firm_jun_wmf": 0,
      "firm_jul_wmf": 0,
      "ultima_nfe": "",
      "semana": "2026-W30",
      "data_promessa": "",
      "qty_prometida": "",
      "comentario": "Solicitar promessa."
    },
    {
      "part_number": "51549221",
      "supplier_code": "WMFBR",
      "supplier_name": "CNH Brasil WMF",
      "ship_date": "",
      "impact": "",
      "sharepoint_critico": false,
      "sharepoint_url": "",
      "sharepoint_reason": "",
      "acao_requerida": "Solicitar promessa",
      "past_due_wmf": 93,
      "firm_jun_wmf": 0,
      "firm_jul_wmf": 0,
      "ultima_nfe": "",
      "semana": "2026-W30",
      "data_promessa": "",
      "qty_prometida": "",
      "comentario": "Solicitar promessa."
    },
    {
      "part_number": "51549223",
      "supplier_code": "WMFBR",
      "supplier_name": "CNH Brasil WMF",
      "ship_date": "",
      "impact": "",
      "sharepoint_critico": false,
      "sharepoint_url": "",
      "sharepoint_reason": "",
      "acao_requerida": "Solicitar promessa",
      "past_due_wmf": 93,
      "firm_jun_wmf": 0,
      "firm_jul_wmf": 0,
      "ultima_nfe": "",
      "semana": "2026-W30",
      "data_promessa": "",
      "qty_prometida": "",
      "comentario": "Solicitar promessa."
    },
    {
      "part_number": "51593654",
      "supplier_code": "WMFBR",
      "supplier_name": "CNH Brasil WMF",
      "ship_date": "",
      "impact": "",
      "sharepoint_critico": false,
      "sharepoint_url": "",
      "sharepoint_reason": "",
      "acao_requerida": "Solicitar promessa",
      "past_due_wmf": 150,
      "firm_jun_wmf": 0,
      "firm_jul_wmf": 0,
      "ultima_nfe": "",
      "semana": "2026-W30",
      "data_promessa": "",
      "qty_prometida": "",
      "comentario": "Solicitar promessa."
    },
    {
      "part_number": "51695225",
      "supplier_code": "WMFBR",
      "supplier_name": "CNH Brasil WMF",
      "ship_date": "",
      "impact": "",
      "sharepoint_critico": false,
      "sharepoint_url": "",
      "sharepoint_reason": "",
      "acao_requerida": "Solicitar promessa",
      "past_due_wmf": 150,
      "firm_jun_wmf": 0,
      "firm_jul_wmf": 0,
      "ultima_nfe": "",
      "semana": "2026-W30",
      "data_promessa": "",
      "qty_prometida": "",
      "comentario": "Solicitar promessa."
    },
    {
      "part_number": "84076645",
      "supplier_code": "WMFBR",
      "supplier_name": "CNH Brasil WMF",
      "ship_date": "",
      "impact": "",
      "sharepoint_critico": false,
      "sharepoint_url": "",
      "sharepoint_reason": "",
      "acao_requerida": "Solicitar promessa",
      "past_due_wmf": 26,
      "firm_jun_wmf": 0,
      "firm_jul_wmf": 0,
      "ultima_nfe": "000078184-001",
      "semana": "2026-W30",
      "data_promessa": "",
      "qty_prometida": "",
      "comentario": "Solicitar promessa."
    },
    {
      "part_number": "84128088",
      "supplier_code": "WMFBR",
      "supplier_name": "CNH Brasil WMF",
      "ship_date": "",
      "impact": "",
      "sharepoint_critico": false,
      "sharepoint_url": "",
      "sharepoint_reason": "",
      "acao_requerida": "Solicitar promessa",
      "past_due_wmf": 93,
      "firm_jun_wmf": 0,
      "firm_jul_wmf": 0,
      "ultima_nfe": "",
      "semana": "2026-W30",
      "data_promessa": "",
      "qty_prometida": "",
      "comentario": "Solicitar promessa."
    },
    {
      "part_number": "84338100",
      "supplier_code": "WMFBR",
      "supplier_name": "CNH Brasil WMF",
      "ship_date": "",
      "impact": "",
      "sharepoint_critico": false,
      "sharepoint_url": "",
      "sharepoint_reason": "",
      "acao_requerida": "Solicitar promessa",
      "past_due_wmf": 2,
      "firm_jun_wmf": 0,
      "firm_jul_wmf": 0,
      "ultima_nfe": "",
      "semana": "2026-W30",
      "data_promessa": "",
      "qty_prometida": "",
      "comentario": "Solicitar promessa."
    },
    {
      "part_number": "84574187",
      "supplier_code": "WMFBR",
      "supplier_name": "CNH Brasil WMF",
      "ship_date": "",
      "impact": "",
      "sharepoint_critico": false,
      "sharepoint_url": "",
      "sharepoint_reason": "",
      "acao_requerida": "Solicitar promessa",
      "past_due_wmf": 60,
      "firm_jun_wmf": 0,
      "firm_jul_wmf": 0,
      "ultima_nfe": "",
      "semana": "2026-W30",
      "data_promessa": "",
      "qty_prometida": "",
      "comentario": "Solicitar promessa."
    },
    {
      "part_number": "84588958",
      "supplier_code": "WMFBR",
      "supplier_name": "CNH Brasil WMF",
      "ship_date": "",
      "impact": "",
      "sharepoint_critico": false,
      "sharepoint_url": "",
      "sharepoint_reason": "",
      "acao_requerida": "Solicitar promessa",
      "past_due_wmf": 10,
      "firm_jun_wmf": 0,
      "firm_jul_wmf": 0,
      "ultima_nfe": "",
      "semana": "2026-W30",
      "data_promessa": "",
      "qty_prometida": "",
      "comentario": "Solicitar promessa."
    },
    {
      "part_number": "84589343",
      "supplier_code": "WMFBR",
      "supplier_name": "CNH Brasil WMF",
      "ship_date": "",
      "impact": "",
      "sharepoint_critico": false,
      "sharepoint_url": "",
      "sharepoint_reason": "",
      "acao_requerida": "Solicitar promessa",
      "past_due_wmf": 10,
      "firm_jun_wmf": 0,
      "firm_jul_wmf": 0,
      "ultima_nfe": "",
      "semana": "2026-W30",
      "data_promessa": "",
      "qty_prometida": "",
      "comentario": "Solicitar promessa."
    },
    {
      "part_number": "87300082",
      "supplier_code": "WMFBR",
      "supplier_name": "CNH Brasil WMF",
      "ship_date": "",
      "impact": "",
      "sharepoint_critico": false,
      "sharepoint_url": "",
      "sharepoint_reason": "",
      "acao_requerida": "Solicitar promessa",
      "past_due_wmf": 111,
      "firm_jun_wmf": 52,
      "firm_jul_wmf": 44,
      "ultima_nfe": "000193489-010",
      "semana": "2026-W30",
      "data_promessa": "",
      "qty_prometida": "",
      "comentario": "Solicitar promessa."
    },
    {
      "part_number": "90481046",
      "supplier_code": "WMFBR",
      "supplier_name": "CNH Brasil WMF",
      "ship_date": "",
      "impact": "",
      "sharepoint_critico": false,
      "sharepoint_url": "",
      "sharepoint_reason": "",
      "acao_requerida": "Solicitar promessa",
      "past_due_wmf": 1,
      "firm_jun_wmf": 0,
      "firm_jul_wmf": 0,
      "ultima_nfe": "",
      "semana": "2026-W30",
      "data_promessa": "",
      "qty_prometida": "",
      "comentario": "Solicitar promessa."
    },
    {
      "part_number": "91700978",
      "supplier_code": "WMFBR",
      "supplier_name": "CNH Brasil WMF",
      "ship_date": "",
      "impact": "",
      "sharepoint_critico": false,
      "sharepoint_url": "",
      "sharepoint_reason": "",
      "acao_requerida": "Solicitar promessa",
      "past_due_wmf": 93,
      "firm_jun_wmf": 0,
      "firm_jul_wmf": 0,
      "ultima_nfe": "",
      "semana": "2026-W30",
      "data_promessa": "",
      "qty_prometida": "",
      "comentario": "Solicitar promessa."
    },
    {
      "part_number": "92675548",
      "supplier_code": "WMFBR",
      "supplier_name": "CNH Brasil WMF",
      "ship_date": "",
      "impact": "",
      "sharepoint_critico": false,
      "sharepoint_url": "",
      "sharepoint_reason": "",
      "acao_requerida": "Solicitar promessa",
      "past_due_wmf": 13,
      "firm_jun_wmf": 0,
      "firm_jul_wmf": 0,
      "ultima_nfe": "000064916-003",
      "semana": "2026-W30",
      "data_promessa": "",
      "qty_prometida": "",
      "comentario": "Solicitar promessa."
    },
    {
      "part_number": "92675561",
      "supplier_code": "WMFBR",
      "supplier_name": "CNH Brasil WMF",
      "ship_date": "",
      "impact": "",
      "sharepoint_critico": false,
      "sharepoint_url": "",
      "sharepoint_reason": "",
      "acao_requerida": "Solicitar promessa",
      "past_due_wmf": 16,
      "firm_jun_wmf": 0,
      "firm_jul_wmf": 0,
      "ultima_nfe": "000064916-003",
      "semana": "2026-W30",
      "data_promessa": "",
      "qty_prometida": "",
      "comentario": "Solicitar promessa."
    },
    {
      "part_number": "9576276",
      "supplier_code": "WMFBR",
      "supplier_name": "CNH Brasil WMF",
      "ship_date": "",
      "impact": "",
      "sharepoint_critico": false,
      "sharepoint_url": "",
      "sharepoint_reason": "",
      "acao_requerida": "Solicitar promessa",
      "past_due_wmf": 75,
      "firm_jun_wmf": 0,
      "firm_jul_wmf": 0,
      "ultima_nfe": "",
      "semana": "2026-W30",
      "data_promessa": "",
      "qty_prometida": "",
      "comentario": "Solicitar promessa."
    },
    {
      "part_number": "10516871",
      "supplier_code": "WMFBR",
      "supplier_name": "CNH Brasil WMF",
      "ship_date": "",
      "impact": "",
      "sharepoint_critico": false,
      "sharepoint_url": "",
      "sharepoint_reason": "",
      "acao_requerida": "Solicitar promessa",
      "past_due_wmf": 0,
      "firm_jun_wmf": 0,
      "firm_jul_wmf": 1000,
      "ultima_nfe": "",
      "semana": "2026-W30",
      "data_promessa": "",
      "qty_prometida": "",
      "comentario": "Solicitar promessa."
    },
    {
      "part_number": "11124834",
      "supplier_code": "WMFBR",
      "supplier_name": "CNH Brasil WMF",
      "ship_date": "",
      "impact": "",
      "sharepoint_critico": false,
      "sharepoint_url": "",
      "sharepoint_reason": "",
      "acao_requerida": "Solicitar promessa",
      "past_due_wmf": 0,
      "firm_jun_wmf": 0,
      "firm_jul_wmf": 100,
      "ultima_nfe": "",
      "semana": "2026-W30",
      "data_promessa": "",
      "qty_prometida": "",
      "comentario": "Solicitar promessa."
    },
    {
      "part_number": "14305221",
      "supplier_code": "WMFBR",
      "supplier_name": "CNH Brasil WMF",
      "ship_date": "",
      "impact": "",
      "sharepoint_critico": false,
      "sharepoint_url": "",
      "sharepoint_reason": "",
      "acao_requerida": "Solicitar promessa",
      "past_due_wmf": 0,
      "firm_jun_wmf": 0,
      "firm_jul_wmf": 100,
      "ultima_nfe": "",
      "semana": "2026-W30",
      "data_promessa": "",
      "qty_prometida": "",
      "comentario": "Solicitar promessa."
    },
    {
      "part_number": "14442431",
      "supplier_code": "WMFBR",
      "supplier_name": "CNH Brasil WMF",
      "ship_date": "",
      "impact": "",
      "sharepoint_critico": false,
      "sharepoint_url": "",
      "sharepoint_reason": "",
      "acao_requerida": "Solicitar promessa",
      "past_due_wmf": 0,
      "firm_jun_wmf": 0,
      "firm_jul_wmf": 100,
      "ultima_nfe": "",
      "semana": "2026-W30",
      "data_promessa": "",
      "qty_prometida": "",
      "comentario": "Solicitar promessa."
    },
    {
      "part_number": "280244",
      "supplier_code": "WMFBR",
      "supplier_name": "CNH Brasil WMF",
      "ship_date": "",
      "impact": "",
      "sharepoint_critico": false,
      "sharepoint_url": "",
      "sharepoint_reason": "",
      "acao_requerida": "Solicitar promessa",
      "past_due_wmf": 0,
      "firm_jun_wmf": 150,
      "firm_jul_wmf": 0,
      "ultima_nfe": "",
      "semana": "2026-W30",
      "data_promessa": "",
      "qty_prometida": "",
      "comentario": "Solicitar promessa."
    },
    {
      "part_number": "43118",
      "supplier_code": "WMFBR",
      "supplier_name": "CNH Brasil WMF",
      "ship_date": "",
      "impact": "",
      "sharepoint_critico": false,
      "sharepoint_url": "",
      "sharepoint_reason": "",
      "acao_requerida": "Solicitar promessa",
      "past_due_wmf": 0,
      "firm_jun_wmf": 0,
      "firm_jul_wmf": 42,
      "ultima_nfe": "000027790-010",
      "semana": "2026-W30",
      "data_promessa": "",
      "qty_prometida": "",
      "comentario": "Solicitar promessa."
    },
    {
      "part_number": "47539577",
      "supplier_code": "WMFBR",
      "supplier_name": "CNH Brasil WMF",
      "ship_date": "",
      "impact": "",
      "sharepoint_critico": false,
      "sharepoint_url": "",
      "sharepoint_reason": "",
      "acao_requerida": "Solicitar promessa",
      "past_due_wmf": 0,
      "firm_jun_wmf": 0,
      "firm_jul_wmf": 100,
      "ultima_nfe": "",
      "semana": "2026-W30",
      "data_promessa": "",
      "qty_prometida": "",
      "comentario": "Solicitar promessa."
    },
    {
      "part_number": "47568404",
      "supplier_code": "WMFBR",
      "supplier_name": "CNH Brasil WMF",
      "ship_date": "",
      "impact": "",
      "sharepoint_critico": false,
      "sharepoint_url": "",
      "sharepoint_reason": "",
      "acao_requerida": "Solicitar promessa",
      "past_due_wmf": 0,
      "firm_jun_wmf": 150,
      "firm_jul_wmf": 0,
      "ultima_nfe": "",
      "semana": "2026-W30",
      "data_promessa": "",
      "qty_prometida": "",
      "comentario": "Solicitar promessa."
    },
    {
      "part_number": "47575960",
      "supplier_code": "WMFBR",
      "supplier_name": "CNH Brasil WMF",
      "ship_date": "",
      "impact": "",
      "sharepoint_critico": false,
      "sharepoint_url": "",
      "sharepoint_reason": "",
      "acao_requerida": "Solicitar promessa",
      "past_due_wmf": 0,
      "firm_jun_wmf": 0,
      "firm_jul_wmf": 0,
      "ultima_nfe": "WMF-003156/2026",
      "semana": "2026-W30",
      "data_promessa": "",
      "qty_prometida": "",
      "comentario": "Solicitar promessa."
    },
    {
      "part_number": "47800545",
      "supplier_code": "WMFBR",
      "supplier_name": "CNH Brasil WMF",
      "ship_date": "",
      "impact": "",
      "sharepoint_critico": false,
      "sharepoint_url": "",
      "sharepoint_reason": "",
      "acao_requerida": "Solicitar promessa",
      "past_due_wmf": 0,
      "firm_jun_wmf": 0,
      "firm_jul_wmf": 0,
      "ultima_nfe": "",
      "semana": "2026-W30",
      "data_promessa": "",
      "qty_prometida": "",
      "comentario": "Solicitar promessa."
    },
    {
      "part_number": "47904311",
      "supplier_code": "WMFBR",
      "supplier_name": "CNH Brasil WMF",
      "ship_date": "",
      "impact": "",
      "sharepoint_critico": false,
      "sharepoint_url": "",
      "sharepoint_reason": "",
      "acao_requerida": "Solicitar promessa",
      "past_due_wmf": 0,
      "firm_jun_wmf": 0,
      "firm_jul_wmf": 16,
      "ultima_nfe": "",
      "semana": "2026-W30",
      "data_promessa": "",
      "qty_prometida": "",
      "comentario": "Solicitar promessa."
    },
    {
      "part_number": "47934543",
      "supplier_code": "WMFBR",
      "supplier_name": "CNH Brasil WMF",
      "ship_date": "",
      "impact": "",
      "sharepoint_critico": false,
      "sharepoint_url": "",
      "sharepoint_reason": "",
      "acao_requerida": "Solicitar promessa",
      "past_due_wmf": 0,
      "firm_jun_wmf": 15,
      "firm_jul_wmf": 0,
      "ultima_nfe": "",
      "semana": "2026-W30",
      "data_promessa": "",
      "qty_prometida": "",
      "comentario": "Solicitar promessa."
    },
    {
      "part_number": "48059748",
      "supplier_code": "WMFBR",
      "supplier_name": "CNH Brasil WMF",
      "ship_date": "",
      "impact": "",
      "sharepoint_critico": false,
      "sharepoint_url": "",
      "sharepoint_reason": "",
      "acao_requerida": "Solicitar promessa",
      "past_due_wmf": 0,
      "firm_jun_wmf": 92,
      "firm_jul_wmf": 0,
      "ultima_nfe": "",
      "semana": "2026-W30",
      "data_promessa": "",
      "qty_prometida": "",
      "comentario": "Solicitar promessa."
    },
    {
      "part_number": "48065724",
      "supplier_code": "WMFBR",
      "supplier_name": "CNH Brasil WMF",
      "ship_date": "",
      "impact": "",
      "sharepoint_critico": false,
      "sharepoint_url": "",
      "sharepoint_reason": "",
      "acao_requerida": "Solicitar promessa",
      "past_due_wmf": 0,
      "firm_jun_wmf": 0,
      "firm_jul_wmf": 43,
      "ultima_nfe": "",
      "semana": "2026-W30",
      "data_promessa": "",
      "qty_prometida": "",
      "comentario": "Solicitar promessa."
    },
    {
      "part_number": "48182269",
      "supplier_code": "WMFBR",
      "supplier_name": "CNH Brasil WMF",
      "ship_date": "",
      "impact": "",
      "sharepoint_critico": false,
      "sharepoint_url": "",
      "sharepoint_reason": "",
      "acao_requerida": "Solicitar promessa",
      "past_due_wmf": 0,
      "firm_jun_wmf": 0,
      "firm_jul_wmf": 80,
      "ultima_nfe": "",
      "semana": "2026-W30",
      "data_promessa": "",
      "qty_prometida": "",
      "comentario": "Solicitar promessa."
    },
    {
      "part_number": "4899093",
      "supplier_code": "WMFBR",
      "supplier_name": "CNH Brasil WMF",
      "ship_date": "",
      "impact": "",
      "sharepoint_critico": false,
      "sharepoint_url": "",
      "sharepoint_reason": "",
      "acao_requerida": "Solicitar promessa",
      "past_due_wmf": 0,
      "firm_jun_wmf": 0,
      "firm_jul_wmf": 100,
      "ultima_nfe": "",
      "semana": "2026-W30",
      "data_promessa": "",
      "qty_prometida": "",
      "comentario": "Solicitar promessa."
    },
    {
      "part_number": "51429208",
      "supplier_code": "WMFBR",
      "supplier_name": "CNH Brasil WMF",
      "ship_date": "",
      "impact": "",
      "sharepoint_critico": false,
      "sharepoint_url": "",
      "sharepoint_reason": "",
      "acao_requerida": "Solicitar promessa",
      "past_due_wmf": 0,
      "firm_jun_wmf": 50,
      "firm_jul_wmf": 0,
      "ultima_nfe": "",
      "semana": "2026-W30",
      "data_promessa": "",
      "qty_prometida": "",
      "comentario": "Solicitar promessa."
    },
    {
      "part_number": "51429211",
      "supplier_code": "WMFBR",
      "supplier_name": "CNH Brasil WMF",
      "ship_date": "",
      "impact": "",
      "sharepoint_critico": false,
      "sharepoint_url": "",
      "sharepoint_reason": "",
      "acao_requerida": "Solicitar promessa",
      "past_due_wmf": 0,
      "firm_jun_wmf": 50,
      "firm_jul_wmf": 0,
      "ultima_nfe": "",
      "semana": "2026-W30",
      "data_promessa": "",
      "qty_prometida": "",
      "comentario": "Solicitar promessa."
    },
    {
      "part_number": "51481654",
      "supplier_code": "WMFBR",
      "supplier_name": "CNH Brasil WMF",
      "ship_date": "",
      "impact": "",
      "sharepoint_critico": false,
      "sharepoint_url": "",
      "sharepoint_reason": "",
      "acao_requerida": "Solicitar promessa",
      "past_due_wmf": 0,
      "firm_jun_wmf": 0,
      "firm_jul_wmf": 0,
      "ultima_nfe": "WMF-003204",
      "semana": "2026-W30",
      "data_promessa": "",
      "qty_prometida": "",
      "comentario": "Solicitar promessa."
    },
    {
      "part_number": "51514080",
      "supplier_code": "WMFBR",
      "supplier_name": "CNH Brasil WMF",
      "ship_date": "",
      "impact": "",
      "sharepoint_critico": false,
      "sharepoint_url": "",
      "sharepoint_reason": "",
      "acao_requerida": "Solicitar promessa",
      "past_due_wmf": 0,
      "firm_jun_wmf": 0,
      "firm_jul_wmf": 0,
      "ultima_nfe": "",
      "semana": "2026-W30",
      "data_promessa": "",
      "qty_prometida": "",
      "comentario": "Solicitar promessa."
    },
    {
      "part_number": "82020477",
      "supplier_code": "WMFBR",
      "supplier_name": "CNH Brasil WMF",
      "ship_date": "",
      "impact": "",
      "sharepoint_critico": false,
      "sharepoint_url": "",
      "sharepoint_reason": "",
      "acao_requerida": "Solicitar promessa",
      "past_due_wmf": 0,
      "firm_jun_wmf": 0,
      "firm_jul_wmf": 0,
      "ultima_nfe": "",
      "semana": "2026-W30",
      "data_promessa": "",
      "qty_prometida": "",
      "comentario": "Solicitar promessa."
    },
    {
      "part_number": "82028028",
      "supplier_code": "WMFBR",
      "supplier_name": "CNH Brasil WMF",
      "ship_date": "",
      "impact": "",
      "sharepoint_critico": false,
      "sharepoint_url": "",
      "sharepoint_reason": "",
      "acao_requerida": "Solicitar promessa",
      "past_due_wmf": 0,
      "firm_jun_wmf": 0,
      "firm_jul_wmf": 100,
      "ultima_nfe": "",
      "semana": "2026-W30",
      "data_promessa": "",
      "qty_prometida": "",
      "comentario": "Solicitar promessa."
    },
    {
      "part_number": "82028480",
      "supplier_code": "WMFBR",
      "supplier_name": "CNH Brasil WMF",
      "ship_date": "",
      "impact": "",
      "sharepoint_critico": false,
      "sharepoint_url": "",
      "sharepoint_reason": "",
      "acao_requerida": "Solicitar promessa",
      "past_due_wmf": 0,
      "firm_jun_wmf": 0,
      "firm_jul_wmf": 100,
      "ultima_nfe": "",
      "semana": "2026-W30",
      "data_promessa": "",
      "qty_prometida": "",
      "comentario": "Solicitar promessa."
    },
    {
      "part_number": "83904573",
      "supplier_code": "WMFBR",
      "supplier_name": "CNH Brasil WMF",
      "ship_date": "",
      "impact": "",
      "sharepoint_critico": false,
      "sharepoint_url": "",
      "sharepoint_reason": "",
      "acao_requerida": "Solicitar promessa",
      "past_due_wmf": 0,
      "firm_jun_wmf": 0,
      "firm_jul_wmf": 1040,
      "ultima_nfe": "",
      "semana": "2026-W30",
      "data_promessa": "",
      "qty_prometida": "",
      "comentario": "Solicitar promessa."
    },
    {
      "part_number": "83999876",
      "supplier_code": "WMFBR",
      "supplier_name": "CNH Brasil WMF",
      "ship_date": "",
      "impact": "",
      "sharepoint_critico": false,
      "sharepoint_url": "",
      "sharepoint_reason": "",
      "acao_requerida": "Solicitar promessa",
      "past_due_wmf": 0,
      "firm_jun_wmf": 150,
      "firm_jul_wmf": 0,
      "ultima_nfe": "",
      "semana": "2026-W30",
      "data_promessa": "",
      "qty_prometida": "",
      "comentario": "Solicitar promessa."
    },
    {
      "part_number": "84000314",
      "supplier_code": "WMFBR",
      "supplier_name": "CNH Brasil WMF",
      "ship_date": "",
      "impact": "",
      "sharepoint_critico": false,
      "sharepoint_url": "",
      "sharepoint_reason": "",
      "acao_requerida": "Solicitar promessa",
      "past_due_wmf": 0,
      "firm_jun_wmf": 120,
      "firm_jul_wmf": 0,
      "ultima_nfe": "000686723-011",
      "semana": "2026-W30",
      "data_promessa": "",
      "qty_prometida": "",
      "comentario": "Solicitar promessa."
    },
    {
      "part_number": "84254513",
      "supplier_code": "WMFBR",
      "supplier_name": "CNH Brasil WMF",
      "ship_date": "",
      "impact": "",
      "sharepoint_critico": false,
      "sharepoint_url": "",
      "sharepoint_reason": "",
      "acao_requerida": "Solicitar promessa",
      "past_due_wmf": 0,
      "firm_jun_wmf": 0,
      "firm_jul_wmf": 0,
      "ultima_nfe": "WMF-003209",
      "semana": "2026-W30",
      "data_promessa": "",
      "qty_prometida": "",
      "comentario": "Solicitar promessa."
    },
    {
      "part_number": "84276155",
      "supplier_code": "WMFBR",
      "supplier_name": "CNH Brasil WMF",
      "ship_date": "",
      "impact": "",
      "sharepoint_critico": false,
      "sharepoint_url": "",
      "sharepoint_reason": "",
      "acao_requerida": "Solicitar promessa",
      "past_due_wmf": 0,
      "firm_jun_wmf": 0,
      "firm_jul_wmf": 0,
      "ultima_nfe": "WMF-002778/2025",
      "semana": "2026-W30",
      "data_promessa": "",
      "qty_prometida": "",
      "comentario": "Solicitar promessa."
    },
    {
      "part_number": "84287963",
      "supplier_code": "WMFBR",
      "supplier_name": "CNH Brasil WMF",
      "ship_date": "",
      "impact": "",
      "sharepoint_critico": false,
      "sharepoint_url": "",
      "sharepoint_reason": "",
      "acao_requerida": "Solicitar promessa",
      "past_due_wmf": 0,
      "firm_jun_wmf": 0,
      "firm_jul_wmf": 0,
      "ultima_nfe": "WMF-002988/2025",
      "semana": "2026-W30",
      "data_promessa": "",
      "qty_prometida": "",
      "comentario": "Solicitar promessa."
    },
    {
      "part_number": "84485320",
      "supplier_code": "WMFBR",
      "supplier_name": "CNH Brasil WMF",
      "ship_date": "",
      "impact": "",
      "sharepoint_critico": false,
      "sharepoint_url": "",
      "sharepoint_reason": "",
      "acao_requerida": "Solicitar promessa",
      "past_due_wmf": 0,
      "firm_jun_wmf": 0,
      "firm_jul_wmf": 0,
      "ultima_nfe": "WMF-002333/2025",
      "semana": "2026-W30",
      "data_promessa": "",
      "qty_prometida": "",
      "comentario": "Solicitar promessa."
    },
    {
      "part_number": "84556758",
      "supplier_code": "WMFBR",
      "supplier_name": "CNH Brasil WMF",
      "ship_date": "",
      "impact": "",
      "sharepoint_critico": false,
      "sharepoint_url": "",
      "sharepoint_reason": "",
      "acao_requerida": "Solicitar promessa",
      "past_due_wmf": 0,
      "firm_jun_wmf": 150,
      "firm_jul_wmf": 0,
      "ultima_nfe": "",
      "semana": "2026-W30",
      "data_promessa": "",
      "qty_prometida": "",
      "comentario": "Solicitar promessa."
    },
    {
      "part_number": "86511325",
      "supplier_code": "WMFBR",
      "supplier_name": "CNH Brasil WMF",
      "ship_date": "",
      "impact": "",
      "sharepoint_critico": false,
      "sharepoint_url": "",
      "sharepoint_reason": "",
      "acao_requerida": "Solicitar promessa",
      "past_due_wmf": 0,
      "firm_jun_wmf": 0,
      "firm_jul_wmf": 100,
      "ultima_nfe": "",
      "semana": "2026-W30",
      "data_promessa": "",
      "qty_prometida": "",
      "comentario": "Solicitar promessa."
    },
    {
      "part_number": "87000148",
      "supplier_code": "WMFBR",
      "supplier_name": "CNH Brasil WMF",
      "ship_date": "",
      "impact": "",
      "sharepoint_critico": false,
      "sharepoint_url": "",
      "sharepoint_reason": "",
      "acao_requerida": "Solicitar promessa",
      "past_due_wmf": 0,
      "firm_jun_wmf": 0,
      "firm_jul_wmf": 100,
      "ultima_nfe": "",
      "semana": "2026-W30",
      "data_promessa": "",
      "qty_prometida": "",
      "comentario": "Solicitar promessa."
    },
    {
      "part_number": "87109716",
      "supplier_code": "WMFBR",
      "supplier_name": "CNH Brasil WMF",
      "ship_date": "",
      "impact": "",
      "sharepoint_critico": false,
      "sharepoint_url": "",
      "sharepoint_reason": "",
      "acao_requerida": "Solicitar promessa",
      "past_due_wmf": 0,
      "firm_jun_wmf": 0,
      "firm_jul_wmf": 0,
      "ultima_nfe": "WMF-002579/2025",
      "semana": "2026-W30",
      "data_promessa": "",
      "qty_prometida": "",
      "comentario": "Solicitar promessa."
    },
    {
      "part_number": "87331401",
      "supplier_code": "WMFBR",
      "supplier_name": "CNH Brasil WMF",
      "ship_date": "",
      "impact": "",
      "sharepoint_critico": false,
      "sharepoint_url": "",
      "sharepoint_reason": "",
      "acao_requerida": "Solicitar promessa",
      "past_due_wmf": 0,
      "firm_jun_wmf": 0,
      "firm_jul_wmf": 100,
      "ultima_nfe": "",
      "semana": "2026-W30",
      "data_promessa": "",
      "qty_prometida": "",
      "comentario": "Solicitar promessa."
    },
    {
      "part_number": "90324912",
      "supplier_code": "WMFBR",
      "supplier_name": "CNH Brasil WMF",
      "ship_date": "",
      "impact": "",
      "sharepoint_critico": false,
      "sharepoint_url": "",
      "sharepoint_reason": "",
      "acao_requerida": "Solicitar promessa",
      "past_due_wmf": 0,
      "firm_jun_wmf": 0,
      "firm_jul_wmf": 300,
      "ultima_nfe": "",
      "semana": "2026-W30",
      "data_promessa": "",
      "qty_prometida": "",
      "comentario": "Solicitar promessa."
    },
    {
      "part_number": "90408825",
      "supplier_code": "WMFBR",
      "supplier_name": "CNH Brasil WMF",
      "ship_date": "",
      "impact": "",
      "sharepoint_critico": false,
      "sharepoint_url": "",
      "sharepoint_reason": "",
      "acao_requerida": "Solicitar promessa",
      "past_due_wmf": 0,
      "firm_jun_wmf": 0,
      "firm_jul_wmf": 77,
      "ultima_nfe": "",
      "semana": "2026-W30",
      "data_promessa": "",
      "qty_prometida": "",
      "comentario": "Solicitar promessa."
    },
    {
      "part_number": "91740502",
      "supplier_code": "WMFBR",
      "supplier_name": "CNH Brasil WMF",
      "ship_date": "",
      "impact": "",
      "sharepoint_critico": false,
      "sharepoint_url": "",
      "sharepoint_reason": "",
      "acao_requerida": "Solicitar promessa",
      "past_due_wmf": 0,
      "firm_jun_wmf": 150,
      "firm_jul_wmf": 0,
      "ultima_nfe": "000013103-001",
      "semana": "2026-W30",
      "data_promessa": "",
      "qty_prometida": "",
      "comentario": "Solicitar promessa."
    },
    {
      "part_number": "91740514",
      "supplier_code": "WMFBR",
      "supplier_name": "CNH Brasil WMF",
      "ship_date": "",
      "impact": "",
      "sharepoint_critico": false,
      "sharepoint_url": "",
      "sharepoint_reason": "",
      "acao_requerida": "Solicitar promessa",
      "past_due_wmf": 0,
      "firm_jun_wmf": 0,
      "firm_jul_wmf": 0,
      "ultima_nfe": "000013458-001",
      "semana": "2026-W30",
      "data_promessa": "",
      "qty_prometida": "",
      "comentario": "Solicitar promessa."
    },
    {
      "part_number": "91838083",
      "supplier_code": "WMFBR",
      "supplier_name": "CNH Brasil WMF",
      "ship_date": "",
      "impact": "",
      "sharepoint_critico": false,
      "sharepoint_url": "",
      "sharepoint_reason": "",
      "acao_requerida": "Solicitar promessa",
      "past_due_wmf": 0,
      "firm_jun_wmf": 0,
      "firm_jul_wmf": 0,
      "ultima_nfe": "000103926-010",
      "semana": "2026-W30",
      "data_promessa": "",
      "qty_prometida": "",
      "comentario": "Solicitar promessa."
    },
    {
      "part_number": "92275534",
      "supplier_code": "WMFBR",
      "supplier_name": "CNH Brasil WMF",
      "ship_date": "",
      "impact": "",
      "sharepoint_critico": false,
      "sharepoint_url": "",
      "sharepoint_reason": "",
      "acao_requerida": "Solicitar promessa",
      "past_due_wmf": 0,
      "firm_jun_wmf": 10,
      "firm_jul_wmf": 0,
      "ultima_nfe": "",
      "semana": "2026-W30",
      "data_promessa": "",
      "qty_prometida": "",
      "comentario": "Solicitar promessa."
    },
    {
      "part_number": "92713907",
      "supplier_code": "WMFBR",
      "supplier_name": "CNH Brasil WMF",
      "ship_date": "",
      "impact": "",
      "sharepoint_critico": false,
      "sharepoint_url": "",
      "sharepoint_reason": "",
      "acao_requerida": "Solicitar promessa",
      "past_due_wmf": 0,
      "firm_jun_wmf": 0,
      "firm_jul_wmf": 20,
      "ultima_nfe": "",
      "semana": "2026-W30",
      "data_promessa": "",
      "qty_prometida": "",
      "comentario": "Solicitar promessa."
    }
  ]
}