{
  "supplier_code": "BNL72",
  "supplier_name": "METALURGICA FIMAC LTDA",
  "semana": "S28/2026",
  "enviado_em": "2026-07-08T15:23:15.299Z",
  "itens": [
    {
      "part_number": "87586665",
      "supplier_code": "BNL72",
      "supplier_name": "METALURGICA FIMAC LTDA",
      "ship_date": "18/06/2026",
      "impact": "3 - No Funcional",
      "sharepoint_critico": false,
      "sharepoint_url": "",
      "acao_requerida": "",
      "past_due_wmf": true,
      "firm_jun_wmf": false,
      "firm_jul_wmf": false,
      "ultima_nfe": "000136043-001",
      "semana": "S28/2026",
      "entrega_confirmada": false,
      "data_promessa": "11/06/2026",
      "qty_prometida": 9,
      "comentario": "foi faturado no dia 11/06 nf 138478"
    },
    {
      "part_number": "90385400",
      "supplier_code": "BNL72",
      "supplier_name": "METALURGICA FIMAC LTDA",
      "ship_date": "29/06/2026",
      "impact": "4 - Stopper",
      "sharepoint_critico": false,
      "sharepoint_url": "",
      "acao_requerida": "",
      "past_due_wmf": true,
      "firm_jun_wmf": false,
      "firm_jul_wmf": false,
      "ultima_nfe": "000137658-001",
      "semana": "S28/2026",
      "entrega_confirmada": false,
      "data_promessa": "24/06/2026",
      "qty_prometida": 50,
      "comentario": "foi faturado no dia 24/06 nf 138678"
    },
    {
      "part_number": "84288671",
      "supplier_code": "BNL72",
      "supplier_name": "METALURGICA FIMAC LTDA",
      "ship_date": "15/07/2026",
      "impact": "4 - Stopper",
      "sharepoint_critico": false,
      "sharepoint_url": "",
      "acao_requerida": "",
      "past_due_wmf": false,
      "firm_jun_wmf": false,
      "firm_jul_wmf": true,
      "ultima_nfe": "000136826-001",
      "semana": "S28/2026",
      "entrega_confirmada": false,
      "data_promessa": "13/07/2026",
      "qty_prometida": 20,
      "comentario": ""
    }
  ],
  "recibido_en_worker": "2026-07-08T15:23:15.401Z"
}